nokoskia/__init__.py
nokoskia/nokoskia.py
nokoskia-4.2.dist-info/METADATA
nokoskia-4.2.dist-info/WHEEL
nokoskia-4.2.dist-info/entry_points.txt
nokoskia-4.2.dist-info/top_level.txt
nokoskia-4.2.dist-info/RECORD
