Metadata-Version: 2.1
Name: nokoskia
Version: 4.2
Summary: A fun tool that generates the famous Breaking Bad dialogue in your terminal.
Home-page: UNKNOWN
Author: Pranav S V
Author-email: pranavsv2004@gmail.com
License: UNKNOWN
Keywords: python,breakingbad,movie,fun,funny tools,command line tool
Platform: UNKNOWN
Classifier: Development Status :: 5 - Production/Stable
Classifier: Intended Audience :: End Users/Desktop
Classifier: Programming Language :: Python :: 3
Classifier: Operating System :: Unix
Classifier: Operating System :: MacOS :: MacOS X
Classifier: Operating System :: Microsoft :: Windows
